pyexr/__init__.py
pyexr/exr.py
pyexr/py.typed
pyexr-0.5.0.dist-info/LICENSE.md
pyexr-0.5.0.dist-info/METADATA
pyexr-0.5.0.dist-info/WHEEL
pyexr-0.5.0.dist-info/RECORD
