Metadata-Version: 2.3
Name: pyexr
Version: 0.5.0
Summary: One line EXR manipulation library
License: MIT
Author: Thijs Vogels
Requires-Python: >=3.8,<4.0
Classifier: License :: OSI Approved :: MIT License
Classifier: Programming Language :: Python :: 3
Classifier: Programming Language :: Python :: 3.8
Classifier: Programming Language :: Python :: 3.9
Classifier: Programming Language :: Python :: 3.10
Classifier: Programming Language :: Python :: 3.11
Classifier: Programming Language :: Python :: 3.12
Classifier: Programming Language :: Python :: 3.13
Requires-Dist: OpenEXR (>=3.2.3)
Requires-Dist: numpy (>=1.20.0) ; python_version < "3.12"
Requires-Dist: numpy (>=1.26.0) ; python_version >= "3.12"
Project-URL: Homepage, https://github.com/tvogels/pyexr
Project-URL: Repository, https://github.com/tvogels/pyexr
